jupyterlab_launcher/__init__.py
jupyterlab_launcher/_version.py
jupyterlab_launcher/app.py
jupyterlab_launcher/error.html
jupyterlab_launcher/handlers.py
jupyterlab_launcher/index.html
jupyterlab_launcher/json_minify.py
jupyterlab_launcher/process.py
jupyterlab_launcher/process_app.py
jupyterlab_launcher/server.py
jupyterlab_launcher/servertest.py
jupyterlab_launcher/settings_handler.py
jupyterlab_launcher/themes_handler.py
jupyterlab_launcher/workspaces_handler.py
jupyterlab_launcher/tests/__init__.py
jupyterlab_launcher/tests/test_settings_api.py
jupyterlab_launcher/tests/test_workspaces_api.py
jupyterlab_launcher/tests/utils.py
jupyterlab_launcher/tests/app-settings/overrides.json
jupyterlab_launcher/tests/schemas/@jupyterlab/apputils-extension/themes.json
jupyterlab_launcher/tests/schemas/@jupyterlab/codemirror-extension/commands.json
jupyterlab_launcher/tests/schemas/@jupyterlab/shortcuts-extension/plugin.json
jupyterlab_launcher/tests/workspaces/abfoo-19e2.jupyterlab-workspace
jupyterlab_launcher/tests/workspaces/abfoo-2c26.jupyterlab-workspace
jupyterlab_launcher-0.13.0.dist-info/DESCRIPTION.rst
jupyterlab_launcher-0.13.0.dist-info/LICENSE.txt
jupyterlab_launcher-0.13.0.dist-info/METADATA
jupyterlab_launcher-0.13.0.dist-info/RECORD
jupyterlab_launcher-0.13.0.dist-info/WHEEL
jupyterlab_launcher-0.13.0.dist-info/metadata.json
jupyterlab_launcher-0.13.0.dist-info/top_level.txt
